pj_rf_sshdb/__init__.py
pj_rf_sshdb/pj_rf_sshdb.py
pj_rf_sshdb-0.1.1.dist-info/METADATA
pj_rf_sshdb-0.1.1.dist-info/WHEEL
pj_rf_sshdb-0.1.1.dist-info/top_level.txt
pj_rf_sshdb-0.1.1.dist-info/RECORD
