Metadata-Version: 2.1
Name: pj-rf-sshdb
Version: 0.1.1
Summary: Get Data from DB via SSh during execution using Robot Framework..
Home-page: https://github.com/
Author: PJ Gevana
Author-email: patdroidz@gmail.com
License: MIT
Platform: UNKNOWN
Classifier: License :: OSI Approved :: MIT License
Classifier: Programming Language :: Python :: 3
Classifier: Programming Language :: Python :: 3.6
Classifier: Programming Language :: Python :: 3.7
Classifier: Programming Language :: Python :: 3.8
